vocalverse/__init__.py
vocalverse/vocalverse.py
vocalverse-1.1.1.dist-info/LICENSE
vocalverse-1.1.1.dist-info/METADATA
vocalverse-1.1.1.dist-info/WHEEL
vocalverse-1.1.1.dist-info/top_level.txt
vocalverse-1.1.1.dist-info/RECORD
