Metadata-Version: 2.1
Name: vocalverse
Version: 1.1.1
Summary: A toolkit for text translation, speech synthesis, and audio transcription
Home-page: https://github.com/Vamshi0104/vocalverse
Author: Vamshi Krishna Madhavan
Author-email: vamshi-madhavan@outlook.com
Classifier: Programming Language :: Python :: 3
Classifier: License :: OSI Approved :: MIT License
Classifier: Operating System :: OS Independent
Requires-Python: >=3.6
License-File: LICENSE
Requires-Dist: pygame
Requires-Dist: googletrans-py
Requires-Dist: gtts
Requires-Dist: pyaudio
Requires-Dist: pydub
Requires-Dist: openai-whisper
